rms_web_scraper/__init__.py
rms_web_scraper/__version__.py
rms_web_scraper/exceptions.py
rms_web_scraper/telerik.py
rms_web_scraper/util.py
rms_web_scraper/clients/__init__.py
rms_web_scraper/clients/base.py
rms_web_scraper/clients/excel.py
rms_web_scraper-0.2.0.dist-info/LICENSE
rms_web_scraper-0.2.0.dist-info/METADATA
rms_web_scraper-0.2.0.dist-info/WHEEL
rms_web_scraper-0.2.0.dist-info/top_level.txt
rms_web_scraper-0.2.0.dist-info/RECORD
