Metadata-Version: 2.1
Name: rms-web-scraper
Version: 0.2.0
Summary: Access DASH RMS data
Home-page: https://github.com/newvicx/rms_web_scraper
Author: Chris Newville
Author-email: chrisnewville1396@gmail.com
License: MIT
Project-URL: Changelog, https://github.com/newvicx/rms_web_scraper/blob/master/CHANGELOG.md
Project-URL: Source, https://github.com/newvicx/rms_web_scraper
Platform: UNKNOWN
Classifier: Development Status :: 4 - Beta
Classifier: Environment :: Web Environment
Classifier: Intended Audience :: Developers
Classifier: License :: OSI Approved :: MIT License
Classifier: Operating System :: Microsoft :: Windows
Classifier: Topic :: Internet :: WWW/HTTP
Classifier: Framework :: AsyncIO
Classifier: Programming Language :: Python :: 3
Requires-Python: >=3.6
License-File: LICENSE
Requires-Dist: httpx (>=0.22.0)
Requires-Dist: beautifulsoup4 (>=4.11.0)
Requires-Dist: pandas (>=1.4.2)
Requires-Dist: openpyxl (>=3.0.9)
Requires-Dist: cachetools (>=5.0.0)
